arcana/dirtree/__init__.py
arcana/dirtree/_version.py
arcana/dirtree/data/__init__.py
arcana/dirtree/data/store.py
arcana/dirtree/data/tests/test_store.py
arcana_dirtree-0.2.4.dist-info/LICENSE
arcana_dirtree-0.2.4.dist-info/WHEEL
arcana_dirtree-0.2.4.dist-info/METADATA
arcana_dirtree-0.2.4.dist-info/RECORD
